echome/__init__.py
echome/exceptions.py
echome/identity.py
echome/keys.py
echome/kube.py
echome/network.py
echome/resource.py
echome/session.py
echome/vm.py
tests/__init__.py
tests/test_keys.py
tests/test_resource.py
tests/test_session.py
tests/test_vm.py
echome_sdk-0.5.1.dist-info/LICENSE
echome_sdk-0.5.1.dist-info/METADATA
echome_sdk-0.5.1.dist-info/WHEEL
echome_sdk-0.5.1.dist-info/top_level.txt
echome_sdk-0.5.1.dist-info/RECORD
