Metadata-Version: 2.1
Name: echome-sdk
Version: 0.5.1
Summary: EcHome python library
Home-page: https://github.com/mgtrrz/echome-python-sdk
Author: Marcus Gutierrez
Author-email: markg90@gmail.com
License: UNKNOWN
Platform: UNKNOWN
Classifier: Programming Language :: Python :: 3
Classifier: License :: OSI Approved :: MIT License
Classifier: Operating System :: OS Independent
Requires-Python: >=3.6
License-File: LICENSE
Requires-Dist: requests (>=2.26)
